jsonpath_tp/__init__.py
jsonpath_tp/traverser_functions.py
jsonpath_tp/compile/__init__.py
jsonpath_tp/compile/compile.py
jsonpath_tp/compile/compile_error.py
jsonpath_tp/compile/function_resolver.py
jsonpath_tp/compile/parser.py
jsonpath_tp/compile/regular_expression.py
jsonpath_tp-1.0.1.dist-info/LICENSE.md
jsonpath_tp-1.0.1.dist-info/METADATA
jsonpath_tp-1.0.1.dist-info/WHEEL
jsonpath_tp-1.0.1.dist-info/top_level.txt
jsonpath_tp-1.0.1.dist-info/zip-safe
jsonpath_tp-1.0.1.dist-info/RECORD
