Metadata-Version: 2.1
Name: jsonpath-tp
Version: 1.0.1
Summary: A jsonpath implementation powered by treepath technology.
Home-page: https://github.com/monkeydevtools/jsonpath_tp
Author: "Joey Sullivan",
Author-email: "monkeydevtools@gmail.com"
License: "Apache Software License"
Platform: any
Classifier: Programming Language :: Python :: 3.7
Classifier: Programming Language :: Python :: 3.8
Classifier: Programming Language :: Python :: 3.9
Classifier: Programming Language :: Python :: 3.10
Classifier: Programming Language :: Python :: 3.11
Classifier: License :: OSI Approved :: Apache Software License
Classifier: Operating System :: OS Independent
Requires-Python: >=3.7
License-File: LICENSE.md
Requires-Dist: treepath
